xr2_sdk/__init__.py
xr2_sdk/client.py
xr2_sdk/config.py
xr2_sdk/models.py
xr2_sdk-0.2.4.dist-info/METADATA
xr2_sdk-0.2.4.dist-info/WHEEL
xr2_sdk-0.2.4.dist-info/top_level.txt
xr2_sdk-0.2.4.dist-info/RECORD
