Metadata-Version: 2.4
Name: xr2-sdk
Version: 0.2.4
Summary: Official Python SDK for xR2 product API
Author-email: xR2 <hello@xr2.uk>
License: MIT
Keywords: xr2,prompts management,sdk
Requires-Python: >=3.9
Requires-Dist: requests>=2.31.0
Requires-Dist: httpx>=0.27.0
Requires-Dist: pydantic>=2.5.0
Requires-Dist: typing-extensions>=4.8.0
